sharetrace/__init__.py
sharetrace/interface.py
sharetrace/sharetrace
sharetrace/sharetrace.py
sharetrace/sharetrace.venv.pth
sharetrace/sharetrace_demo
sharetrace/sharetrace_demo.py
sharetrace/sharetrace_demo.venv.pth
sharetrace/st.py
sharetrace/util/click_utils.py
sharetrace/util/console_utils.py
sharetrace-1.0.0.dist-info/WHEEL
sharetrace-1.0.0.dist-info/METADATA
sharetrace-1.0.0.dist-info/entry_points.txt
sharetrace-1.0.0.data/data/share/completions/sharetrace-completion.bash
sharetrace-1.0.0.data/data/share/completions/sharetrace_demo-completion.bash
sharetrace-1.0.0.dist-info/RECORD
