Metadata-Version: 2.1
Name: sharetrace
License: MIT
Summary: Capture and share detailed traceback information
Project-URL: Issues, https://github.com/RyanDraves/sharetrace/issues
Project-URL: Repository, https://github.com/RyanDraves/sharetrace
Requires-Python: >=3.10
Requires-Dist: inquirerpy<1,>=0.3.4
Requires-Dist: jinja2<4,>=3.1.0
Requires-Dist: marshmallow-dataclass<9,>=8.7.1
Requires-Dist: pygments<3,>=2.16.0
Requires-Dist: rich<14,>=13.9.4
Requires-Dist: rich-click<2,>=1.8.3
Version: 1.0.0
